[{"prenom":"joueur","nom":"joueur","login":"joueur","password":"joueur","confirm_password":"joueur","score":115,"avatar":"langage-python.jpg"},{"prenom":"Niankou","nom":"Falamaaleene","login":"niankou","password":"lew","confirm_password":"lew","score":44,"avatar":"c++.png"},{"prenom":"Diogaye","nom":"sene","login":"dioks","password":"dioks","confirm_password":"dioks","score":20,"avatar":"web.png"},{"prenom":"Sakhir","nom":"Fall","login":"sakhir","password":"passer","confirm_password":"passer","score":115,"avatar":"Fall.jpg"},{"prenom":"Aule","nom":"Nianga","login":"aule","password":"aule","confirm_password":"aule","score":25,"avatar":"php.png"},{"prenom":"Ibrahima ","nom":"Gueye","login":"ibou","password":"oums","confirm_password":"oums","score":120,"avatar":"langage-python.jpg"},{"prenom":"Imam","nom":"Diallo","login":"dials","password":"poulo","confirm_password":"poulo","score":110,"avatar":"web.png"},{"prenom":"Madior","nom":"Sene","login":"madior","password":"madior","confirm_password":"madior","score":0,"avatar":"php.png"}]